setup.py
OurTools.egg-info/PKG-INFO
OurTools.egg-info/SOURCES.txt
OurTools.egg-info/dependency_links.txt
OurTools.egg-info/requires.txt
OurTools.egg-info/top_level.txt
ourtools/__init__.py
ourtools/ourtools.py