Metadata-Version: 1.0
Name: OurTools
Version: 0.0.12
Summary: A Tool Project by CHIANDYAO
Home-page: UNKNOWN
Author: UNKNOWN
Author-email: UNKNOWN
License: UNKNOWN
Platform: any
